Decode/CtrlUnit.v
// module control_unit (
//     input  [6:0] opcode,
//     input  [2:0] funct3,
//     input        funct7b5,
//     input        funct7b0,
//     output reg       RegWrite,
//     output reg [1:0] ResultSrc,
//     output reg       MemWrite,
//     output reg       Jump,
//     output reg       Branch,
//     output reg [4:0] ALUControl,
//     output reg       ALUSrc,
//     output reg [2:0] ImmSrc
// );

//     // ALU operation codes (based on ALU.txt and control_unit.txt)
//     localparam [4:0]
//         OP_ADD    = 5'b00000,
//         OP_SUB    = 5'b00010,
//         OP_SLL    = 5'b00100,
//         OP_SLT    = 5'b01000,
//         OP_SLTU   = 5'b01100,
//         OP_XOR    = 5'b10000,
//         OP_SRL    = 5'b10100,
//         OP_SRA    = 5'b10110,
//         OP_OR     = 5'b11000,
//         OP_AND    = 5'b11100,
//         // M extension
//         OP_MUL    = 5'b00001,
//         OP_MULH   = 5'b00101,
//         OP_MULHSU = 5'b01101,
//         OP_MULHU  = 5'b01001,
//         OP_DIV    = 5'b10001,
//         OP_DIVU   = 5'b10101,
//         OP_REM    = 5'b11001,
//         OP_REMU   = 5'b11101,
//         OP_NOP    = 5'b11111;

//     // Immediate selection codes (see Immediate_extender.txt)
//     localparam [2:0]
//         IMM_U      = 3'b000,
//         IMM_J      = 3'b001,
//         IMM_B      = 3'b010,
//         IMM_S      = 3'b011,
//         IMM_I      = 3'b100,
//         IMM_I_SHFT = 3'b101,
//         IMM_IU     = 3'b111;

//     // ResultSrc codes
//     localparam [1:0]
//         RES_ALU  = 2'b00,
//         RES_MEM  = 2'b01,
//         RES_IMM  = 2'b10,
//         RES_PC4  = 2'b11;

//     always @* begin
//         // Default values
//         RegWrite   = 1'b0;
//         ResultSrc  = RES_ALU;
//         MemWrite   = 1'b0;
//         Jump       = 1'b0;
//         Branch     = 1'b0;
//         ALUControl = OP_NOP;
//         ALUSrc     = 1'b0;
//         ImmSrc     = IMM_I;

//         case (opcode)
//             7'b0110011: begin // R-type (including M extension)
//                 RegWrite = 1'b1;
//                 ALUSrc   = 1'b0;
//                 case (funct3)
//                     3'b000: begin
//                         if      (funct7b0 == 1'b0 && funct7b5 == 1'b0) ALUControl = OP_ADD;    // ADD
//                         else if (funct7b0 == 1'b0 && funct7b5 == 1'b1) ALUControl = OP_SUB;    // SUB
//                         else if (funct7b0 == 1'b1 && funct7b5 == 1'b0) ALUControl = OP_MUL;    // MUL
//                         else ALUControl = OP_NOP;
//                     end
//                     3'b001: ALUControl = (funct7b0 == 1'b0) ? OP_SLL : OP_MULH;                // SLL/MULH
//                     3'b010: ALUControl = (funct7b0 == 1'b0) ? OP_SLT : OP_MULHSU;              // SLT/MULHSU
//                     3'b011: ALUControl = (funct7b0 == 1'b0) ? OP_SLTU : OP_MULHU;              // SLTU/MULHU
//                     3'b100: ALUControl = (funct7b0 == 1'b0) ? OP_XOR : OP_DIV;                 // XOR/DIV
//                     3'b101: begin
//                         if      (funct7b0 == 1'b0 && funct7b5 == 1'b0) ALUControl = OP_SRL;    // SRL
//                         else if (funct7b0 == 1'b0 && funct7b5 == 1'b1) ALUControl = OP_SRA;    // SRA
//                         else if (funct7b0 == 1'b1 && funct7b5 == 1'b0) ALUControl = OP_DIVU;   // DIVU
//                         else ALUControl = OP_NOP;
//                     end
//                     3'b110: ALUControl = (funct7b0 == 1'b0) ? OP_OR : OP_REM;                  // OR/REM
//                     3'b111: ALUControl = (funct7b0 == 1'b0) ? OP_AND : OP_REMU;                // AND/REMU
//                     default: ALUControl = OP_NOP;
//                 endcase
//             end
//             7'b0010011: begin // I-type ALU
//                 RegWrite = 1'b1;
//                 ALUSrc   = 1'b1;
//                 case (funct3)
//                     3'b000: ALUControl = OP_ADD; ImmSrc = IMM_I;
//                     3'b010: ALUControl = OP_SLT; ImmSrc = IMM_I;
//                     3'b011: ALUControl = OP_SLTU; ImmSrc = IMM_IU;
//                     3'b100: ALUControl = OP_XOR; ImmSrc = IMM_I;
//                     3'b110: ALUControl = OP_OR;  ImmSrc = IMM_I;
//                     3'b111: ALUControl = OP_AND; ImmSrc = IMM_I;
//                     3'b001: ALUControl = OP_SLL; ImmSrc = IMM_I_SHFT;
//                     3'b101: begin
//                         ImmSrc = IMM_I_SHFT;
//                         if (funct7b5 == 1'b0) ALUControl = OP_SRL;
//                         else                  ALUControl = OP_SRA;
//                     end
//                     default: ALUControl = OP_NOP;
//                 endcase
//             end
//             7'b0000011: begin // Loads
//                 RegWrite  = 1'b1;
//                 ALUSrc    = 1'b1;
//                 ResultSrc = RES_MEM;
//                 ALUControl= OP_ADD;
//                 ImmSrc    = IMM_I;
//             end
//             7'b0100011: begin // Stores
//                 MemWrite  = 1'b1;
//                 ALUSrc    = 1'b1;
//                 ALUControl= OP_ADD;
//                 ImmSrc    = IMM_S;
//             end
//             7'b1100011: begin // Branches
//                 Branch    = 1'b1;
//                 ALUControl= OP_SUB;
//                 ImmSrc    = IMM_B;
//             end
//             7'b1101111: begin // JAL
//                 RegWrite  = 1'b1;
//                 Jump      = 1'b1;
//                 ResultSrc = RES_PC4;
//                 ALUControl= OP_ADD;
//                 ImmSrc    = IMM_J;
//             end
//             7'b1100111: begin // JALR
//                 RegWrite  = 1'b1;
//                 Jump      = 1'b1;
//                 ResultSrc = RES_PC4;
//                 ALUControl= OP_ADD;
//                 ImmSrc    = IMM_I;
//             end
//             7'b0110111: begin // LUI
//                 RegWrite  = 1'b1;
//                 ResultSrc = RES_IMM;
//                 ALUControl= OP_ADD;
//                 ImmSrc    = IMM_U;
//             end
//             7'b0010111: begin // AUIPC
//                 RegWrite  = 1'b1;
//                 ResultSrc = RES_ALU;
//                 ALUControl= OP_ADD;
//                 ImmSrc    = IMM_U;
//             end
//             default: begin
//                 RegWrite   = 1'b0;
//                 ResultSrc  = RES_ALU;
//                 MemWrite   = 1'b0;
//                 Jump       = 1'b0;
//                 Branch     = 1'b0;
//                 ALUControl = OP_NOP;
//                 ALUSrc     = 1'b0;
//                 ImmSrc     = IMM_I;
//             end
//         endcase
//     end
// endmodule












module control_unit (
    input  [6:0] opcode,
    input  [2:0] funct3,
    input        funct7b5,
    input        funct7b0,
    output reg       RegWrite,
    output reg [1:0] ResultSrc,
    output reg       MemWrite,
    output reg       Jump,
    output reg       Branch,
    output reg [4:0] ALUControl,
    output reg       ALUSrc,
    output reg [2:0] ImmSrc
);

    // ALU operation codes
    localparam [4:0]
        OP_ADD    = 5'b00000,
        OP_SUB    = 5'b00010,
        OP_SLL    = 5'b00100,
        OP_SLT    = 5'b01000,
        OP_SLTU   = 5'b01100,
        OP_XOR    = 5'b10000,
        OP_SRL    = 5'b10100,
        OP_SRA    = 5'b10110,
        OP_OR     = 5'b11000,
        OP_AND    = 5'b11100,
        // M extension
        OP_MUL    = 5'b00001,
        OP_MULH   = 5'b00101,
        OP_MULHSU = 5'b01101,
        OP_MULHU  = 5'b01001,
        OP_DIV    = 5'b10001,
        OP_DIVU   = 5'b10101,
        OP_REM    = 5'b11001,
        OP_REMU   = 5'b11101,
        OP_NOP    = 5'b11111;

    // Immediate selection codes
    localparam [2:0]
        IMM_U      = 3'b000,
        IMM_J      = 3'b001,
        IMM_B      = 3'b010,
        IMM_S      = 3'b011,
        IMM_I      = 3'b100,
        IMM_I_SHFT = 3'b101,
        IMM_IU     = 3'b111;

    // ResultSrc codes
    localparam [1:0]
        RES_ALU  = 2'b00,
        RES_MEM  = 2'b01,
        RES_IMM  = 2'b10,
        RES_PC4  = 2'b11;

    always @* begin
        // Default values
        RegWrite   = 1'b0;
        ResultSrc  = RES_ALU;
        MemWrite   = 1'b0;
        Jump       = 1'b0;
        Branch     = 1'b0;
        ALUControl = OP_NOP;
        ALUSrc     = 1'b0;
        ImmSrc     = IMM_I;

        case (opcode)
            7'b0110011: begin // R-type (including M extension)
                RegWrite = 1'b1;
                ALUSrc   = 1'b0;
                if (funct7b5 == 1'b0 && funct7b0 == 1'b1) begin // M-extension (funct7 = 7'b0000001)
                    case (funct3)
                        3'b000: ALUControl = OP_MUL;    // MUL
                        3'b001: ALUControl = OP_MULH;   // MULH
                        3'b010: ALUControl = OP_MULHSU; // MULHSU
                        3'b011: ALUControl = OP_MULHU;  // MULHU
                        3'b100: ALUControl = OP_DIV;    // DIV
                        3'b101: ALUControl = OP_DIVU;   // DIVU
                        3'b110: ALUControl = OP_REM;    // REM
                        3'b111: ALUControl = OP_REMU;   // REMU
                        default: ALUControl = OP_NOP;
                    endcase
                end else begin // Standard R-type
                    case (funct3)
                        3'b000: begin
                            if (funct7b5 == 1'b0) ALUControl = OP_ADD; // ADD
                            else ALUControl = OP_SUB;                  // SUB
                        end
                        3'b001: ALUControl = OP_SLL;   // SLL
                        3'b010: ALUControl = OP_SLT;   // SLT
                        3'b011: ALUControl = OP_SLTU;  // SLTU
                        3'b100: ALUControl = OP_XOR;   // XOR
                        3'b101: begin
                            if (funct7b5 == 1'b0) ALUControl = OP_SRL; // SRL
                            else ALUControl = OP_SRA;                  // SRA
                        end
                        3'b110: ALUControl = OP_OR;    // OR
                        3'b111: ALUControl = OP_AND;   // AND
                        default: ALUControl = OP_NOP;
                    endcase
                end
            end
            7'b0010011: begin // I-type ALU
                RegWrite = 1'b1;
                ALUSrc   = 1'b1;
                case (funct3)
                    3'b000: begin
                        ALUControl = OP_ADD;
                        ImmSrc = IMM_I;
                    end
                    3'b010: begin
                        ALUControl = OP_SLT;
                        ImmSrc = IMM_I;
                    end
                    3'b011: begin
                        ALUControl = OP_SLTU;
                        ImmSrc = IMM_I;
                    end
                    3'b100: begin
                        ALUControl = OP_XOR;
                        ImmSrc = IMM_I;
                    end
                    3'b110: begin
                        ALUControl = OP_OR;
                        ImmSrc = IMM_I;
                    end
                    3'b111: begin
                        ALUControl = OP_AND;
                        ImmSrc = IMM_I;
                    end
                    3'b001: begin
                        ALUControl = OP_SLL;
                        ImmSrc = IMM_I_SHFT;
                    end
                    3'b101: begin
                        ImmSrc = IMM_I_SHFT;
                        if (funct7b5 == 1'b0) ALUControl = OP_SRL; // SRLI
                        else ALUControl = OP_SRA;                  // SRAI
                    end
                    default: ALUControl = OP_NOP;
                endcase
            end
            7'b0000011: begin // Loads
                RegWrite  = 1'b1;
                ALUSrc    = 1'b1;
                ResultSrc = RES_MEM;
                ALUControl= OP_ADD;
                ImmSrc    = IMM_I;
            end
            7'b0100011: begin // Stores
                MemWrite  = 1'b1;
                ALUSrc    = 1'b1;
                ALUControl= OP_ADD;
                ImmSrc    = IMM_S;
            end
            7'b1100011: begin // Branches
                Branch    = 1'b1;
                ALUSrc    = 1'b0;
                ImmSrc    = IMM_B;
                case (funct3)
                    3'b000: ALUControl = OP_SUB; // BEQ
                    3'b001: ALUControl = OP_SUB; // BNE
                    3'b100: ALUControl = OP_SLT; // BLT
                    3'b101: ALUControl = OP_SLT; // BGE
                    3'b110: ALUControl = OP_SLTU; // BLTU
                    3'b111: ALUControl = OP_SLTU; // BGEU
                    default: ALUControl = OP_NOP;
                endcase
            end
            7'b1101111: begin // JAL
                RegWrite  = 1'b1;
                Jump      = 1'b1;
                ResultSrc = RES_PC4;
                ALUControl= OP_ADD;
                ImmSrc    = IMM_J;
            end
            7'b1100111: begin // JALR
                RegWrite  = 1'b1;
                Jump      = 1'b1;
                ResultSrc = RES_PC4;
                ALUControl= OP_ADD;
                ALUSrc    = 1'b1;
                ImmSrc    = IMM_I;
            end
            7'b0110111: begin // LUI
                RegWrite  = 1'b1;
                ResultSrc = RES_IMM;
                ALUControl= OP_ADD;
                ImmSrc    = IMM_U;
            end
            7'b0010111: begin // AUIPC
                RegWrite  = 1'b1;
                ResultSrc = RES_ALU;
                ALUControl= OP_ADD;
                ALUSrc    = 1'b1;
                ImmSrc    = IMM_U;
            end
            default: begin
                RegWrite   = 1'b0;
                ResultSrc  = RES_ALU;
                MemWrite   = 1'b0;
                Jump       = 1'b0;
                Branch     = 1'b0;
                ALUControl = OP_NOP;
                ALUSrc     = 1'b0;
                ImmSrc     = IMM_I;
            end
        endcase
    end
endmodule

Decode/CtrlUnit_tb.v
`timescale 1ns / 1ps
`include "CtrlUnit.v"
module control_unit_tb;

    // Inputs
    reg [6:0] opcode;
    reg [2:0] funct3;
    reg funct7b5;
    reg funct7b0;

    // Outputs
    wire RegWrite;
    wire [1:0] ResultSrc;
    wire MemWrite;
    wire Jump;
    wire Branch;
    wire [4:0] ALUControl;
    wire ALUSrc;
    wire [2:0] ImmSrc;

    // Instantiate the Unit Under Test (UUT)
    control_unit uut (
        .opcode(opcode),
        .funct3(funct3),
        .funct7b5(funct7b5),
        .funct7b0(funct7b0),
        .RegWrite(RegWrite),
        .ResultSrc(ResultSrc),
        .MemWrite(MemWrite),
        .Jump(Jump),
        .Branch(Branch),
        .ALUControl(ALUControl),
        .ALUSrc(ALUSrc),
        .ImmSrc(ImmSrc)
    );

    // Logging function to display signals
    task log_signals;
        input [31:0] test_num;
        input [99:0] instr_name;
        begin
            $display("Test %0d: %s", test_num, instr_name);
            $display("  Inputs:  opcode=0x%h, funct3=0x%h, funct7b5=%b, funct7b0=%b",
                     opcode, funct3, funct7b5, funct7b0);
            $display("  Outputs: RegWrite=%b, ResultSrc=0x%h, MemWrite=%b, Jump=%b, Branch=%b, ALUControl=0x%h, ALUSrc=%b, ImmSrc=0x%h",
                     RegWrite, ResultSrc, MemWrite, Jump, Branch, ALUControl, ALUSrc, ImmSrc);
            $display("--------------------------------------------------");
        end
    endtask

    initial begin
        // Initialize VCD dump
        $dumpfile("control_unit_tb.vcd");
        $dumpvars(0, control_unit_tb);

        // Initialize inputs
        opcode = 7'b0;
        funct3 = 3'b0;
        funct7b5 = 1'b0;
        funct7b0 = 1'b0;

        // Test cases
        #10;
        // Test 1: R-type ADD (opcode=0110011, funct3=000, funct7=0000000)
        opcode = 7'b0110011; funct3 = 3'b000; funct7b5 = 1'b0; funct7b0 = 1'b0;
        #10;
        log_signals(1, "R-type ADD");
        // Expected: RegWrite=1, ResultSrc=00, MemWrite=0, Jump=0, Branch=0, ALUControl=00000, ALUSrc=0, ImmSrc=100

        // Test 2: R-type MUL (opcode=0110011, funct3=000, funct7=0000001)
        opcode = 7'b0110011; funct3 = 3'b000; funct7b5 = 1'b0; funct7b0 = 1'b1;
        #10;
        log_signals(2, "R-type MUL");
        // Expected: RegWrite=1, ResultSrc=00, MemWrite=0, Jump=0, Branch=0, ALUControl=00001, ALUSrc=0, ImmSrc=100

        // Test 3: I-type ADDI (opcode=0010011, funct3=000)
        opcode = 7'b0010011; funct3 = 3'b000; funct7b5 = 1'b0; funct7b0 = 1'b0;
        #10;
        log_signals(3, "I-type ADDI");
        // Expected: RegWrite=1, ResultSrc=00, MemWrite=0, Jump=0, Branch=0, ALUControl=00000, ALUSrc=1, ImmSrc=100

        // Test 4: I-type SRAI (opcode=0010011, funct3=101, funct7b5=1)
        opcode = 7'b0010011; funct3 = 3'b101; funct7b5 = 1'b1; funct7b0 = 1'b0;
        #10;
        log_signals(4, "I-type SRAI");
        // Expected: RegWrite=1, ResultSrc=00, MemWrite=0, Jump=0, Branch=0, ALUControl=10110, ALUSrc=1, ImmSrc=101

        // Test 5: Load (opcode=0000011, funct3=010)
        opcode = 7'b0000011; funct3 = 3'b010; funct7b5 = 1'b0; funct7b0 = 1'b0;
        #10;
        log_signals(5, "Load (LW)");
        // Expected: RegWrite=1, ResultSrc=01, MemWrite=0, Jump=0, Branch=0, ALUControl=00000, ALUSrc=1, ImmSrc=100

        // Test 6: Store (opcode=0100011, funct3=010)
        opcode = 7'b0100011; funct3 = 3'b010; funct7b5 = 1'b0; funct7b0 = 1'b0;
        #10;
        log_signals(6, "Store (SW)");
        // Expected: RegWrite=0, ResultSrc=00, MemWrite=1, Jump=0, Branch=0, ALUControl=00000, ALUSrc=1, ImmSrc=011

        // Test 7: Branch BEQ (opcode=1100011, funct3=000)
        opcode = 7'b1100011; funct3 = 3'b000; funct7b5 = 1'b0; funct7b0 = 1'b0;
        #10;
        log_signals(7, "Branch (BEQ)");
        // Expected: RegWrite=0, ResultSrc=00, MemWrite=0, Jump=0, Branch=1, ALUControl=00010, ALUSrc=0, ImmSrc=010

        // Test 8: JAL (opcode=1101111)
        opcode = 7'b1101111; funct3 = 3'b000; funct7b5 = 1'b0; funct7b0 = 1'b0;
        #10;
        log_signals(8, "JAL");
        // Expected: RegWrite=1, ResultSrc=11, MemWrite=0, Jump=1, Branch=0, ALUControl=00000, ALUSrc=0, ImmSrc=001

        // Test 9: JALR (opcode=1100111)
        opcode = 7'b1100111; funct3 = 3'b000; funct7b5 = 1'b0; funct7b0 = 1'b0;
        #10;
        log_signals(9, "JALR");
        // Expected: RegWrite=1, ResultSrc=11, MemWrite=0, Jump=1, Branch=0, ALUControl=00000, ALUSrc=1, ImmSrc=100

        // Test 10: LUI (opcode=0110111)
        opcode = 7'b0110111; funct3 = 3'b000; funct7b5 = 1'b0; funct7b0 = 1'b0;
        #10;
        log_signals(10, "LUI");
        // Expected: RegWrite=1, ResultSrc=10, MemWrite=0, Jump=0, Branch=0, ALUControl=00000, ALUSrc=0, ImmSrc=000

        // Test 11: AUIPC (opcode=0010111)
        opcode = 7'b0010111; funct3 = 3'b000; funct7b5 = 1'b0; funct7b0 = 1'b0;
        #10;
        log_signals(11, "AUIPC");
        // Expected: RegWrite=1, ResultSrc=00, MemWrite=0, Jump=0, Branch=0, ALUControl=00000, ALUSrc=1, ImmSrc=000

        // Test 12: Invalid opcode
        opcode = 7'b1111111; funct3 = 3'b000; funct7b5 = 1'b0; funct7b0 = 1'b0;
        #10;
        log_signals(12, "Invalid Opcode");
        // Expected: RegWrite=0, ResultSrc=00, MemWrite=0, Jump=0, Branch=0, ALUControl=11111, ALUSrc=0, ImmSrc=100

        // End simulation
        #10;
        $finish;
    end

endmodule

Decode/control_unit_tb.vcd
$date
	Wed Apr 30 01:51:29 2025
$end
$version
	Icarus Verilog
$end
$timescale
	1ps
$end
$scope module control_unit_tb $end
$var wire 2 ! ResultSrc [1:0] $end
$var wire 1 " RegWrite $end
$var wire 1 # MemWrite $end
$var wire 1 $ Jump $end
$var wire 3 % ImmSrc [2:0] $end
$var wire 1 & Branch $end
$var wire 1 ' ALUSrc $end
$var wire 5 ( ALUControl [4:0] $end
$var reg 3 ) funct3 [2:0] $end
$var reg 1 * funct7b0 $end
$var reg 1 + funct7b5 $end
$var reg 7 , opcode [6:0] $end
$scope module uut $end
$var wire 3 - funct3 [2:0] $end
$var wire 1 * funct7b0 $end
$var wire 1 + funct7b5 $end
$var wire 7 . opcode [6:0] $end
$var parameter 3 / IMM_B $end
$var parameter 3 0 IMM_I $end
$var parameter 3 1 IMM_IU $end
$var parameter 3 2 IMM_I_SHFT $end
$var parameter 3 3 IMM_J $end
$var parameter 3 4 IMM_S $end
$var parameter 3 5 IMM_U $end
$var parameter 5 6 OP_ADD $end
$var parameter 5 7 OP_AND $end
$var parameter 5 8 OP_DIV $end
$var parameter 5 9 OP_DIVU $end
$var parameter 5 : OP_MUL $end
$var parameter 5 ; OP_MULH $end
$var parameter 5 < OP_MULHSU $end
$var parameter 5 = OP_MULHU $end
$var parameter 5 > OP_NOP $end
$var parameter 5 ? OP_OR $end
$var parameter 5 @ OP_REM $end
$var parameter 5 A OP_REMU $end
$var parameter 5 B OP_SLL $end
$var parameter 5 C OP_SLT $end
$var parameter 5 D OP_SLTU $end
$var parameter 5 E OP_SRA $end
$var parameter 5 F OP_SRL $end
$var parameter 5 G OP_SUB $end
$var parameter 5 H OP_XOR $end
$var parameter 2 I RES_ALU $end
$var parameter 2 J RES_IMM $end
$var parameter 2 K RES_MEM $end
$var parameter 2 L RES_PC4 $end
$var reg 5 M ALUControl [4:0] $end
$var reg 1 ' ALUSrc $end
$var reg 1 & Branch $end
$var reg 3 N ImmSrc [2:0] $end
$var reg 1 $ Jump $end
$var reg 1 # MemWrite $end
$var reg 1 " RegWrite $end
$var reg 2 O ResultSrc [1:0] $end
$upscope $end
$scope task log_signals $end
$var reg 100 P instr_name [99:0] $end
$var reg 32 Q test_num [31:0] $end
$upscope $end
$upscope $end
$enddefinitions $end
$comment Show the parameter values. $end
$dumpall
b11 L
b1 K
b10 J
b0 I
b10000 H
b10 G
b10100 F
b10110 E
b1100 D
b1000 C
b100 B
b11101 A
b11001 @
b11000 ?
b11111 >
b1001 =
b1101 <
b101 ;
b1 :
b10101 9
b10001 8
b11100 7
b0 6
b0 5
b11 4
b1 3
b101 2
b111 1
b100 0
b10 /
$end
#0
$dumpvars
bx Q
bx P
b0 O
b100 N
b11111 M
b0 .
b0 -
b0 ,
0+
0*
b0 )
b11111 (
0'
0&
b100 %
0$
0#
0"
b0 !
$end
#10000
b0 (
b0 M
1"
b110011 ,
b110011 .
#20000
b1 (
b1 M
1"
1*
b1010010001011010111010001111001011100000110010100100000010000010100010001000100 P
b1 Q
#30000
1'
b0 (
b0 M
1"
0*
b10011 ,
b10011 .
b1010010001011010111010001111001011100000110010100100000010011010101010101001100 P
b10 Q
#40000
b101 %
b101 N
1'
b10110 (
b10110 M
1"
1+
b101 )
b101 -
b100100100101101011101000111100101110000011001010010000001000001010001000100010001001001 P
b11 Q
#50000
b1 !
b1 O
b100 %
b100 N
1'
b0 (
b0 M
1"
0+
b10 )
b10 -
b11 ,
b11 .
b100100100101101011101000111100101110000011001010010000001010011010100100100000101001001 P
b100 Q
#60000
b11 %
b11 N
1#
1'
b0 (
b0 M
b0 !
b0 O
0"
b100011 ,
b100011 .
b10011000110111101100001011001000010000000101000010011000101011100101001 P
b101 Q
#70000
1&
b10 %
b10 N
0'
b10 (
b10 M
0#
b0 )
b0 -
b1100011 ,
b1100011 .
b1010011011101000110111101110010011001010010000000101000010100110101011100101001 P
b110 Q
#80000
b11 !
b11 O
1$
1"
b1 %
b1 N
b0 (
b0 M
0&
b1101111 ,
b1101111 .
b10000100111001001100001011011100110001101101000001000000010100001000010010001010101000100101001 P
b111 Q
#90000
1'
b100 %
b100 N
b0 (
b0 M
1$
b11 !
b11 O
1"
b1100111 ,
b1100111 .
b10010100100000101001100 P
b1000 Q
#100000
b0 %
b0 N
0'
b0 (
b0 M
0$
b10 !
b10 O
1"
b110111 ,
b110111 .
b1001010010000010100110001010010 P
b1001 Q
#110000
1'
b0 %
b0 N
b0 (
b0 M
b0 !
b0 O
1"
b10111 ,
b10111 .
b10011000101010101001001 P
b1010 Q
#120000
b100 %
b100 N
0'
b11111 (
b11111 M
0"
b1111111 ,
b1111111 .
b100000101010101010010010101000001000011 P
b1011 Q
#130000
b1110011101100110000101101100011010010110010000100000010011110111000001100011011011110110010001100101 P
b1100 Q
